{
  "book": "genesis",
  "chapter": 22,
  "verses": {
    "1": {
      "reference": "창세기 22:1",
      "verseText": "וַיְהִי אַחַר הַדְּבָרִים הָאֵלֶּה וְהָאֱלֹהִים נִסָּה אֶת־אַבְרָהָם וַיֹּאמֶר אֵלָיו אַבְרָהָם וַיֹּאמֶר הִנֵּנִי׃",
      "kor2": "그리고-있었다 그-일들 후에 그-이것들 그리고-그-하나님 시험하였다 את-아브라함 그리고-말하였다 אליו 아브라함 그리고-말하였다 הנהני",
      "words": [
        {
          "text": "וַיְהִי",
          "meaning": "",
          "pron": "",
          "morph": "",
          "root": "",
          "kor": ""
        },
        {
          "text": "אַחַר",
          "meaning": "",
          "pron": "",
          "morph": "",
          "root": "",
          "kor": ""
        },
        {
          "text": "הַדְּבָרִים",
          "meaning": "",
          "pron": "",
          "morph": "",
          "root": "",
          "kor": ""
        },
        {
          "text": "הָאֵלֶּה",
          "meaning": "",
          "pron": "",
          "morph": "",
          "root": "",
          "kor": ""
        },
        {
          "text": "וְהָאֱלֹהִים",
          "meaning": "",
          "pron": "",
          "morph": "",
          "root": "",
          "kor": ""
        },
        {
          "text": "נִסָּה",
          "meaning": "",
          "pron": "",
          "morph": "",
          "root": "",
          "kor": ""
        },
        {
          "text": "אֶת־אַבְרָהָם",
          "meaning": "",
          "pron": "",
          "morph": "",
          "root": "",
          "kor": ""
        },
        {
          "text": "וַיֹּאמֶר",
          "meaning": "",
          "pron": "",
          "morph": "",
          "root": "",
          "kor": ""
        },
        {
          "text": "אֵלָיו",
          "meaning": "",
          "pron": "",
          "morph": "",
          "root": "",
          "kor": ""
        },
        {
          "text": "אַבְרָהָם",
          "meaning": "",
          "pron": "",
          "morph": "",
          "root": "",
          "kor": ""
        },
        {
          "text": "וַיֹּאמֶר",
          "meaning": "",
          "pron": "",
          "morph": "",
          "root": "",
          "kor": ""
        },
        {
          "text": "הִנֵּנִי׃",
          "meaning": "",
          "pron": "",
          "morph": "",
          "root": "",
          "kor": ""
        }
      ]
    },
    "2": {
      "reference": "창세기 22:2",
      "verseText": "וַיֹּאמֶר קַח־נָא אֶת־בִּנְךָ אֶת־יְחִידְךָ אֲשֶׁר־אָהַבְתָּ אֶת־יִצְחָק וְלֶךְ־לְךָ אֶל־אֶרֶץ הַמֹּרִיָּה וְהַעֲלֵהוּ שָׁם לְעֹלָה עַל אַחַד הֶהָרִים אֲשֶׁר אֹמַר אֵלֶיךָ׃",
      "kor2": "그리고-말하였다 취하라-제발 את-아들-네 את-유일한-네 אשר-사랑하였다 את-이삭 그리고-가라-너를 אל-땅 그-모리아 그리고-올려라-그 שם 번제로 על אחד 그-산들 אשר 말할 אליך",
      "words": [
        {
          "text": "וַיֹּאמֶר",
          "meaning": "",
          "pron": "",
          "morph": "",
          "root": "",
          "kor": ""
        },
        {
          "text": "קַח־נָא",
          "meaning": "",
          "pron": "",
          "morph": "",
          "root": "",
          "kor": ""
        },
        {
          "text": "אֶת־בִּנְךָ",
          "meaning": "",
          "pron": "",
          "morph": "",
          "root": "",
          "kor": ""
        },
        {
          "text": "אֶת־יְחִידְךָ",
          "meaning": "",
          "pron": "",
          "morph": "",
          "root": "",
          "kor": ""
        },
        {
          "text": "אֲשֶׁר־אָהַבְתָּ",
          "meaning": "",
          "pron": "",
          "morph": "",
          "root": "",
          "kor": ""
        },
        {
          "text": "אֶת־יִצְחָק",
          "meaning": "",
          "pron": "",
          "morph": "",
          "root": "",
          "kor": ""
        },
        {
          "text": "וְלֶךְ־לְךָ",
          "meaning": "",
          "pron": "",
          "morph": "",
          "root": "",
          "kor": ""
        },
        {
          "text": "אֶל־אֶרֶץ",
          "meaning": "",
          "pron": "",
          "morph": "",
          "root": "",
          "kor": ""
        },
        {
          "text": "הַמֹּרִיָּה",
          "meaning": "",
          "pron": "",
          "morph": "",
          "root": "",
          "kor": ""
        },
        {
          "text": "וְהַעֲלֵהוּ",
          "meaning": "",
          "pron": "",
          "morph": "",
          "root": "",
          "kor": ""
        },
        {
          "text": "שָׁם",
          "meaning": "",
          "pron": "",
          "morph": "",
          "root": "",
          "kor": ""
        },
        {
          "text": "לְעֹלָה",
          "meaning": "",
          "pron": "",
          "morph": "",
          "root": "",
          "kor": ""
        },
        {
          "text": "עַל",
          "meaning": "",
          "pron": "",
          "morph": "",
          "root": "",
          "kor": ""
        },
        {
          "text": "אַחַד",
          "meaning": "",
          "pron": "",
          "morph": "",
          "root": "",
          "kor": ""
        },
        {
          "text": "הֶהָרִים",
          "meaning": "",
          "pron": "",
          "morph": "",
          "root": "",
          "kor": ""
        },
        {
          "text": "אֲשֶׁר",
          "meaning": "",
          "pron": "",
          "morph": "",
          "root": "",
          "kor": ""
        },
        {
          "text": "אֹמַר",
          "meaning": "",
          "pron": "",
          "morph": "",
          "root": "",
          "kor": ""
        },
        {
          "text": "אֵלֶיךָ׃",
          "meaning": "",
          "pron": "",
          "morph": "",
          "root": "",
          "kor": ""
        }
      ]
    },
    "3": {
      "reference": "창세기 22:3",
      "verseText": "וַיַּשְׁכֵּם אַבְרָהָם בַּבֹּקֶר וַיַּחֲבֹשׁ אֶת־חֲמֹרוֹ וַיִּקַּח אֶת־שְׁנֵי נְעָרָיו אִתּוֹ וְאֵת יִצְחָק בְּנוֹ וַיְבַקַּע עֲצֵי עֹלָה וַיָּקָם וַיֵּלֶךְ אֶל־הַמָּקוֹם אֲשֶׁר־אָמַר־לוֹ הָאֱלֹהִים׃",
      "kor2": "그리고-일찍-일어났다 아브라함 בבוקר 그리고-안장-지웠다 את-나귀-그의 그리고-취하였다 את-두 소년-그의 איתו 그리고-את 이삭 아들-그의 그리고-쪼갰다 나무들 번제 그리고-일어났다 그리고-갔다 אל-그-장소 אשר-말하였다-לו 그-하나님",
      "words": [
        {
          "text": "וַיַּשְׁכֵּם",
          "meaning": "",
          "pron": "",
          "morph": "",
          "root": "",
          "kor": ""
        },
        {
          "text": "אַבְרָהָם",
          "meaning": "",
          "pron": "",
          "morph": "",
          "root": "",
          "kor": ""
        },
        {
          "text": "בַּבֹּקֶר",
          "meaning": "",
          "pron": "",
          "morph": "",
          "root": "",
          "kor": ""
        },
        {
          "text": "וַיַּחֲבֹשׁ",
          "meaning": "",
          "pron": "",
          "morph": "",
          "root": "",
          "kor": ""
        },
        {
          "text": "אֶת־חֲמֹרוֹ",
          "meaning": "",
          "pron": "",
          "morph": "",
          "root": "",
          "kor": ""
        },
        {
          "text": "וַיִּקַּח",
          "meaning": "",
          "pron": "",
          "morph": "",
          "root": "",
          "kor": ""
        },
        {
          "text": "אֶת־שְׁנֵי",
          "meaning": "",
          "pron": "",
          "morph": "",
          "root": "",
          "kor": ""
        },
        {
          "text": "נְעָרָיו",
          "meaning": "",
          "pron": "",
          "morph": "",
          "root": "",
          "kor": ""
        },
        {
          "text": "אִתּוֹ",
          "meaning": "",
          "pron": "",
          "morph": "",
          "root": "",
          "kor": ""
        },
        {
          "text": "וְאֵת",
          "meaning": "",
          "pron": "",
          "morph": "",
          "root": "",
          "kor": ""
        },
        {
          "text": "יִצְחָק",
          "meaning": "",
          "pron": "",
          "morph": "",
          "root": "",
          "kor": ""
        },
        {
          "text": "בְּנוֹ",
          "meaning": "",
          "pron": "",
          "morph": "",
          "root": "",
          "kor": ""
        },
        {
          "text": "וַיְבַקַּע",
          "meaning": "",
          "pron": "",
          "morph": "",
          "root": "",
          "kor": ""
        },
        {
          "text": "עֲצֵי",
          "meaning": "",
          "pron": "",
          "morph": "",
          "root": "",
          "kor": ""
        },
        {
          "text": "עֹלָה",
          "meaning": "",
          "pron": "",
          "morph": "",
          "root": "",
          "kor": ""
        },
        {
          "text": "וַיָּקָם",
          "meaning": "",
          "pron": "",
          "morph": "",
          "root": "",
          "kor": ""
        },
        {
          "text": "וַיֵּלֶךְ",
          "meaning": "",
          "pron": "",
          "morph": "",
          "root": "",
          "kor": ""
        },
        {
          "text": "אֶל־הַמָּקוֹם",
          "meaning": "",
          "pron": "",
          "morph": "",
          "root": "",
          "kor": ""
        },
        {
          "text": "אֲשֶׁר־אָמַר־לוֹ",
          "meaning": "",
          "pron": "",
          "morph": "",
          "root": "",
          "kor": ""
        },
        {
          "text": "הָאֱלֹהִים׃",
          "meaning": "",
          "pron": "",
          "morph": "",
          "root": "",
          "kor": ""
        }
      ]
    },
    "4": {
      "reference": "창세기 22:4",
      "verseText": "בַּיּוֹם הַשְּׁלִישִׁי וַיִּשָּׂא אַבְרָהָם אֶת־עֵינָיו וַיַּרְא אֶת־הַמָּקוֹם מֵרָחֹק׃",
      "kor2": "그-날 그-셋째에 그리고-들었다 아브라함 את-눈-그의 그리고-보았다 את-그-장소 멀리서",
      "words": [
        {
          "text": "בַּיּוֹם",
          "meaning": "",
          "pron": "",
          "morph": "",
          "root": "",
          "kor": ""
        },
        {
          "text": "הַשְּׁלִישִׁי",
          "meaning": "",
          "pron": "",
          "morph": "",
          "root": "",
          "kor": ""
        },
        {
          "text": "וַיִּשָּׂא",
          "meaning": "",
          "pron": "",
          "morph": "",
          "root": "",
          "kor": ""
        },
        {
          "text": "אַבְרָהָם",
          "meaning": "",
          "pron": "",
          "morph": "",
          "root": "",
          "kor": ""
        },
        {
          "text": "אֶת־עֵינָיו",
          "meaning": "",
          "pron": "",
          "morph": "",
          "root": "",
          "kor": ""
        },
        {
          "text": "וַיַּרְא",
          "meaning": "",
          "pron": "",
          "morph": "",
          "root": "",
          "kor": ""
        },
        {
          "text": "אֶת־הַמָּקוֹם",
          "meaning": "",
          "pron": "",
          "morph": "",
          "root": "",
          "kor": ""
        },
        {
          "text": "מֵרָחֹק׃",
          "meaning": "",
          "pron": "",
          "morph": "",
          "root": "",
          "kor": ""
        }
      ]
    },
    "5": {
      "reference": "창세기 22:5",
      "verseText": "וַיֹּאמֶר אַבְרָהָם אֶל־נְעָרָיו שְׁבוּ־לָכֶם פֹּה עִם־הַחֲמוֹר וַאֲנִי וְהַנַּעַר נֵלְכָה עַד־כֹּה וְנִשְׁתַּחֲוֶה וְנָשׁוּבָה אֲלֵיכֶם׃",
      "kor2": "그리고-말하였다 아브라함 אל-소년들-그의 앉아라-너희 여기 עם-그-나귀 그리고-나 그리고-그-소년 가겠다 עד-여기 그리고-경배하겠다 그리고-돌아오겠다 אליכם",
      "words": [
        {
          "text": "וַיֹּאמֶר",
          "meaning": "",
          "pron": "",
          "morph": "",
          "root": "",
          "kor": ""
        },
        {
          "text": "אַבְרָהָם",
          "meaning": "",
          "pron": "",
          "morph": "",
          "root": "",
          "kor": ""
        },
        {
          "text": "אֶל־נְעָרָיו",
          "meaning": "",
          "pron": "",
          "morph": "",
          "root": "",
          "kor": ""
        },
        {
          "text": "שְׁבוּ־לָכֶם",
          "meaning": "",
          "pron": "",
          "morph": "",
          "root": "",
          "kor": ""
        },
        {
          "text": "פֹּה",
          "meaning": "",
          "pron": "",
          "morph": "",
          "root": "",
          "kor": ""
        },
        {
          "text": "עִם־הַחֲמוֹר",
          "meaning": "",
          "pron": "",
          "morph": "",
          "root": "",
          "kor": ""
        },
        {
          "text": "וַאֲנִי",
          "meaning": "",
          "pron": "",
          "morph": "",
          "root": "",
          "kor": ""
        },
        {
          "text": "וְהַנַּעַר",
          "meaning": "",
          "pron": "",
          "morph": "",
          "root": "",
          "kor": ""
        },
        {
          "text": "נֵלְכָה",
          "meaning": "",
          "pron": "",
          "morph": "",
          "root": "",
          "kor": ""
        },
        {
          "text": "עַד־כֹּה",
          "meaning": "",
          "pron": "",
          "morph": "",
          "root": "",
          "kor": ""
        },
        {
          "text": "וְנִשְׁתַּחֲוֶה",
          "meaning": "",
          "pron": "",
          "morph": "",
          "root": "",
          "kor": ""
        },
        {
          "text": "וְנָשׁוּבָה",
          "meaning": "",
          "pron": "",
          "morph": "",
          "root": "",
          "kor": ""
        },
        {
          "text": "אֲלֵיכֶם׃",
          "meaning": "",
          "pron": "",
          "morph": "",
          "root": "",
          "kor": ""
        }
      ]
    },
    "6": {
      "reference": "창세기 22:6",
      "verseText": "וַיִּקַּח אַבְרָהָם אֶת־עֲצֵי הָעֹלָה וַיָּשֶׂם עַל־יִצְחָק בְּנוֹ וַיִּקַּח בְּיָדוֹ אֶת־הָאֵשׁ וְאֶת־הַמַּאֲכֶלֶת וַיֵּלְכוּ שְׁנֵיהֶם יַחְדָּו׃",
      "kor2": "그리고-취하였다 아브라함 את-나무들 그-번제 그리고-두었다 על-이삭 아들-그의 그리고-취하였다 בידו את-그-불 그리고-את 그-칼 그리고-갔다 둘-그들 함께",
      "words": [
        {
          "text": "וַיִּקַּח",
          "meaning": "",
          "pron": "",
          "morph": "",
          "root": "",
          "kor": ""
        },
        {
          "text": "אַבְרָהָם",
          "meaning": "",
          "pron": "",
          "morph": "",
          "root": "",
          "kor": ""
        },
        {
          "text": "אֶת־עֲצֵי",
          "meaning": "",
          "pron": "",
          "morph": "",
          "root": "",
          "kor": ""
        },
        {
          "text": "הָעֹלָה",
          "meaning": "",
          "pron": "",
          "morph": "",
          "root": "",
          "kor": ""
        },
        {
          "text": "וַיָּשֶׂם",
          "meaning": "",
          "pron": "",
          "morph": "",
          "root": "",
          "kor": ""
        },
        {
          "text": "עַל־יִצְחָק",
          "meaning": "",
          "pron": "",
          "morph": "",
          "root": "",
          "kor": ""
        },
        {
          "text": "בְּנוֹ",
          "meaning": "",
          "pron": "",
          "morph": "",
          "root": "",
          "kor": ""
        },
        {
          "text": "וַיִּקַּח",
          "meaning": "",
          "pron": "",
          "morph": "",
          "root": "",
          "kor": ""
        },
        {
          "text": "בְּיָדוֹ",
          "meaning": "",
          "pron": "",
          "morph": "",
          "root": "",
          "kor": ""
        },
        {
          "text": "אֶת־הָאֵשׁ",
          "meaning": "",
          "pron": "",
          "morph": "",
          "root": "",
          "kor": ""
        },
        {
          "text": "וְאֶת־הַמַּאֲכֶלֶת",
          "meaning": "",
          "pron": "",
          "morph": "",
          "root": "",
          "kor": ""
        },
        {
          "text": "וַיֵּלְכוּ",
          "meaning": "",
          "pron": "",
          "morph": "",
          "root": "",
          "kor": ""
        },
        {
          "text": "שְׁנֵיהֶם",
          "meaning": "",
          "pron": "",
          "morph": "",
          "root": "",
          "kor": ""
        },
        {
          "text": "יַחְדָּו׃",
          "meaning": "",
          "pron": "",
          "morph": "",
          "root": "",
          "kor": ""
        }
      ]
    },
    "7": {
      "reference": "창세기 22:7",
      "verseText": "וַיֹּאמֶר יִצְחָק אֶל־אַבְרָהָם אָבִיו וַיֹּאמֶר אָבִי וַיֹּאמֶר הִנֶּנִּי בְּנִי וַיֹּאמֶר הִנֵּה הָאֵשׁ וְהָעֵצִים וְאַיֵּה הַשֶּׂה לְעֹלָה׃",
      "kor2": "그리고-말하였다 이삭 אל-아브라함 아버지-그의 그리고-말하였다 아버지-나의 그리고-말하였다 הנהני 아들-나의 그리고-말하였다 보라 그-불 그리고-그-나무들 그리고-어디 그-양 번제로",
      "words": [
        {
          "text": "וַיֹּאמֶר",
          "meaning": "",
          "pron": "",
          "morph": "",
          "root": "",
          "kor": ""
        },
        {
          "text": "יִצְחָק",
          "meaning": "",
          "pron": "",
          "morph": "",
          "root": "",
          "kor": ""
        },
        {
          "text": "אֶל־אַבְרָהָם",
          "meaning": "",
          "pron": "",
          "morph": "",
          "root": "",
          "kor": ""
        },
        {
          "text": "אָבִיו",
          "meaning": "",
          "pron": "",
          "morph": "",
          "root": "",
          "kor": ""
        },
        {
          "text": "וַיֹּאמֶר",
          "meaning": "",
          "pron": "",
          "morph": "",
          "root": "",
          "kor": ""
        },
        {
          "text": "אָבִי",
          "meaning": "",
          "pron": "",
          "morph": "",
          "root": "",
          "kor": ""
        },
        {
          "text": "וַיֹּאמֶר",
          "meaning": "",
          "pron": "",
          "morph": "",
          "root": "",
          "kor": ""
        },
        {
          "text": "הִנֶּנִּי",
          "meaning": "",
          "pron": "",
          "morph": "",
          "root": "",
          "kor": ""
        },
        {
          "text": "בְּנִי",
          "meaning": "",
          "pron": "",
          "morph": "",
          "root": "",
          "kor": ""
        },
        {
          "text": "וַיֹּאמֶר",
          "meaning": "",
          "pron": "",
          "morph": "",
          "root": "",
          "kor": ""
        },
        {
          "text": "הִנֵּה",
          "meaning": "",
          "pron": "",
          "morph": "",
          "root": "",
          "kor": ""
        },
        {
          "text": "הָאֵשׁ",
          "meaning": "",
          "pron": "",
          "morph": "",
          "root": "",
          "kor": ""
        },
        {
          "text": "וְהָעֵצִים",
          "meaning": "",
          "pron": "",
          "morph": "",
          "root": "",
          "kor": ""
        },
        {
          "text": "וְאַיֵּה",
          "meaning": "",
          "pron": "",
          "morph": "",
          "root": "",
          "kor": ""
        },
        {
          "text": "הַשֶּׂה",
          "meaning": "",
          "pron": "",
          "morph": "",
          "root": "",
          "kor": ""
        },
        {
          "text": "לְעֹלָה׃",
          "meaning": "",
          "pron": "",
          "morph": "",
          "root": "",
          "kor": ""
        }
      ]
    },
    "8": {
      "reference": "창세기 22:8",
      "verseText": "וַיֹּאמֶר אַבְרָהָם אֱלֹהִים יִרְאֶה־לּוֹ הַשֶּׂה לְעֹלָה בְּנִי וַיֵּלְכוּ שְׁנֵיהֶם יַחְדָּו׃",
      "kor2": "그리고-말하였다 아브라함 하나님 보실-것이다-לו 그-양 번제로 아들-나의 그리고-갔다 둘-그들 함께",
      "words": [
        {
          "text": "וַיֹּאמֶר",
          "meaning": "",
          "pron": "",
          "morph": "",
          "root": "",
          "kor": ""
        },
        {
          "text": "אַבְרָהָם",
          "meaning": "",
          "pron": "",
          "morph": "",
          "root": "",
          "kor": ""
        },
        {
          "text": "אֱלֹהִים",
          "meaning": "",
          "pron": "",
          "morph": "",
          "root": "",
          "kor": ""
        },
        {
          "text": "יִרְאֶה־לּוֹ",
          "meaning": "",
          "pron": "",
          "morph": "",
          "root": "",
          "kor": ""
        },
        {
          "text": "הַשֶּׂה",
          "meaning": "",
          "pron": "",
          "morph": "",
          "root": "",
          "kor": ""
        },
        {
          "text": "לְעֹלָה",
          "meaning": "",
          "pron": "",
          "morph": "",
          "root": "",
          "kor": ""
        },
        {
          "text": "בְּנִי",
          "meaning": "",
          "pron": "",
          "morph": "",
          "root": "",
          "kor": ""
        },
        {
          "text": "וַיֵּלְכוּ",
          "meaning": "",
          "pron": "",
          "morph": "",
          "root": "",
          "kor": ""
        },
        {
          "text": "שְׁנֵיהֶם",
          "meaning": "",
          "pron": "",
          "morph": "",
          "root": "",
          "kor": ""
        },
        {
          "text": "יַחְדָּו׃",
          "meaning": "",
          "pron": "",
          "morph": "",
          "root": "",
          "kor": ""
        }
      ]
    },
    "9": {
      "reference": "창세기 22:9",
      "verseText": "וַיָּבֹאוּ אֶל־הַמָּקוֹם אֲשֶׁר אָמַר־לוֹ הָאֱלֹהִים וַיִּבֶן שָׁם אַבְרָהָם אֶת־הַמִּזְבֵּחַ וַיַּעֲרֹךְ אֶת־הָעֵצִים וַיַּעֲקֹד אֶת־יִצְחָק בְּנוֹ וַיָּשֶׂם אֹתוֹ עַל־הַמִּזְבֵּחַ מִמַּעַל לָעֵצִים׃",
      "kor2": "그리고-왔다 אל-그-장소 אשר אמר-לו 그-하나님 그리고-세웠다 שם 아브라함 את-그-제단 그리고-정렬하였다 את-그-나무들 그리고-묶었다 את-이삭 아들-그의 그리고-두었다 אותו על-그-제단 ממעל ל-그-나무들",
      "words": [
        {
          "text": "וַיָּבֹאוּ",
          "meaning": "",
          "pron": "",
          "morph": "",
          "root": "",
          "kor": ""
        },
        {
          "text": "אֶל־הַמָּקוֹם",
          "meaning": "",
          "pron": "",
          "morph": "",
          "root": "",
          "kor": ""
        },
        {
          "text": "אֲשֶׁר",
          "meaning": "",
          "pron": "",
          "morph": "",
          "root": "",
          "kor": ""
        },
        {
          "text": "אָמַר־לוֹ",
          "meaning": "",
          "pron": "",
          "morph": "",
          "root": "",
          "kor": ""
        },
        {
          "text": "הָאֱלֹהִים",
          "meaning": "",
          "pron": "",
          "morph": "",
          "root": "",
          "kor": ""
        },
        {
          "text": "וַיִּבֶן",
          "meaning": "",
          "pron": "",
          "morph": "",
          "root": "",
          "kor": ""
        },
        {
          "text": "שָׁם",
          "meaning": "",
          "pron": "",
          "morph": "",
          "root": "",
          "kor": ""
        },
        {
          "text": "אַבְרָהָם",
          "meaning": "",
          "pron": "",
          "morph": "",
          "root": "",
          "kor": ""
        },
        {
          "text": "אֶת־הַמִּזְבֵּחַ",
          "meaning": "",
          "pron": "",
          "morph": "",
          "root": "",
          "kor": ""
        },
        {
          "text": "וַיַּעֲרֹךְ",
          "meaning": "",
          "pron": "",
          "morph": "",
          "root": "",
          "kor": ""
        },
        {
          "text": "אֶת־הָעֵצִים",
          "meaning": "",
          "pron": "",
          "morph": "",
          "root": "",
          "kor": ""
        },
        {
          "text": "וַיַּעֲקֹד",
          "meaning": "",
          "pron": "",
          "morph": "",
          "root": "",
          "kor": ""
        },
        {
          "text": "אֶת־יִצְחָק",
          "meaning": "",
          "pron": "",
          "morph": "",
          "root": "",
          "kor": ""
        },
        {
          "text": "בְּנוֹ",
          "meaning": "",
          "pron": "",
          "morph": "",
          "root": "",
          "kor": ""
        },
        {
          "text": "וַיָּשֶׂם",
          "meaning": "",
          "pron": "",
          "morph": "",
          "root": "",
          "kor": ""
        },
        {
          "text": "אֹתוֹ",
          "meaning": "",
          "pron": "",
          "morph": "",
          "root": "",
          "kor": ""
        },
        {
          "text": "עַל־הַמִּזְבֵּחַ",
          "meaning": "",
          "pron": "",
          "morph": "",
          "root": "",
          "kor": ""
        },
        {
          "text": "מִמַּעַל",
          "meaning": "",
          "pron": "",
          "morph": "",
          "root": "",
          "kor": ""
        },
        {
          "text": "לָעֵצִים׃",
          "meaning": "",
          "pron": "",
          "morph": "",
          "root": "",
          "kor": ""
        }
      ]
    },
    "10": {
      "reference": "창세기 22:10",
      "verseText": "וַיִּשְׁלַח אַבְרָהָם אֶת־יָדוֹ וַיִּקַּח אֶת־הַמַּאֲכֶלֶת לִשְׁחֹט אֶת־בְּנוֹ׃",
      "kor2": "그리고-보냈다 아브라함 את-손-그의 그리고-취하였다 את-그-칼 לשחט את-아들-그의",
      "words": [
        {
          "text": "וַיִּשְׁלַח",
          "meaning": "",
          "pron": "",
          "morph": "",
          "root": "",
          "kor": ""
        },
        {
          "text": "אַבְרָהָם",
          "meaning": "",
          "pron": "",
          "morph": "",
          "root": "",
          "kor": ""
        },
        {
          "text": "אֶת־יָדוֹ",
          "meaning": "",
          "pron": "",
          "morph": "",
          "root": "",
          "kor": ""
        },
        {
          "text": "וַיִּקַּח",
          "meaning": "",
          "pron": "",
          "morph": "",
          "root": "",
          "kor": ""
        },
        {
          "text": "אֶת־הַמַּאֲכֶלֶת",
          "meaning": "",
          "pron": "",
          "morph": "",
          "root": "",
          "kor": ""
        },
        {
          "text": "לִשְׁחֹט",
          "meaning": "",
          "pron": "",
          "morph": "",
          "root": "",
          "kor": ""
        },
        {
          "text": "אֶת־בְּנוֹ׃",
          "meaning": "",
          "pron": "",
          "morph": "",
          "root": "",
          "kor": ""
        }
      ]
    },
    "11": {
      "reference": "창세기 22:11",
      "verseText": "וַיִּקְרָא אֵלָיו מַלְאַךְ יְהוָה מִן־הַשָּׁמַיִם וַיֹּאמֶר אַבְרָהָם אַבְרָהָם וַיֹּאמֶר הִנֵּנִי׃",
      "kor2": "그리고-불렀다 אליו 천사 יהוה מן-그-하늘들 그리고-말하였다 아브라함 아브라함 그리고-말하였다 הנהני",
      "words": [
        {
          "text": "וַיִּקְרָא",
          "meaning": "",
          "pron": "",
          "morph": "",
          "root": "",
          "kor": ""
        },
        {
          "text": "אֵלָיו",
          "meaning": "",
          "pron": "",
          "morph": "",
          "root": "",
          "kor": ""
        },
        {
          "text": "מַלְאַךְ",
          "meaning": "",
          "pron": "",
          "morph": "",
          "root": "",
          "kor": ""
        },
        {
          "text": "יְהוָה",
          "meaning": "",
          "pron": "",
          "morph": "",
          "root": "",
          "kor": ""
        },
        {
          "text": "מִן־הַשָּׁמַיִם",
          "meaning": "",
          "pron": "",
          "morph": "",
          "root": "",
          "kor": ""
        },
        {
          "text": "וַיֹּאמֶר",
          "meaning": "",
          "pron": "",
          "morph": "",
          "root": "",
          "kor": ""
        },
        {
          "text": "אַבְרָהָם",
          "meaning": "",
          "pron": "",
          "morph": "",
          "root": "",
          "kor": ""
        },
        {
          "text": "אַבְרָהָם",
          "meaning": "",
          "pron": "",
          "morph": "",
          "root": "",
          "kor": ""
        },
        {
          "text": "וַיֹּאמֶר",
          "meaning": "",
          "pron": "",
          "morph": "",
          "root": "",
          "kor": ""
        },
        {
          "text": "הִנֵּנִי׃",
          "meaning": "",
          "pron": "",
          "morph": "",
          "root": "",
          "kor": ""
        }
      ]
    },
    "12": {
      "reference": "창세기 22:12",
      "verseText": "וַיֹּאמֶר אַל־תִּשְׁלַח יָדְךָ אֶל־הַנַּעַר וְאַל־תַּעַשׂ לוֹ מְאוּמָה כִּי עַתָּה יָדַעְתִּי כִּי־יְרֵא אֱלֹהִים אַתָּה וְלֹא חָשַׂכְתָּ אֶת־בִּנְךָ אֶת־יְחִידְךָ מִמֶּנִּי׃",
      "kor2": "그리고-말하였다 보내지-말라 손-네 אל-그-소년 그리고-하지-말라 לו 아무것도 כי 이제 알았다 כי-경외 하나님 너 그리고-아끼지-않았다 את-아들-네 את-유일한-네 ממני",
      "words": [
        {
          "text": "וַיֹּאמֶר",
          "meaning": "",
          "pron": "",
          "morph": "",
          "root": "",
          "kor": ""
        },
        {
          "text": "אַל־תִּשְׁלַח",
          "meaning": "",
          "pron": "",
          "morph": "",
          "root": "",
          "kor": ""
        },
        {
          "text": "יָדְךָ",
          "meaning": "",
          "pron": "",
          "morph": "",
          "root": "",
          "kor": ""
        },
        {
          "text": "אֶל־הַנַּעַר",
          "meaning": "",
          "pron": "",
          "morph": "",
          "root": "",
          "kor": ""
        },
        {
          "text": "וְאַל־תַּעַשׂ",
          "meaning": "",
          "pron": "",
          "morph": "",
          "root": "",
          "kor": ""
        },
        {
          "text": "לוֹ",
          "meaning": "",
          "pron": "",
          "morph": "",
          "root": "",
          "kor": ""
        },
        {
          "text": "מְאוּמָה",
          "meaning": "",
          "pron": "",
          "morph": "",
          "root": "",
          "kor": ""
        },
        {
          "text": "כִּי",
          "meaning": "",
          "pron": "",
          "morph": "",
          "root": "",
          "kor": ""
        },
        {
          "text": "עַתָּה",
          "meaning": "",
          "pron": "",
          "morph": "",
          "root": "",
          "kor": ""
        },
        {
          "text": "יָדַעְתִּי",
          "meaning": "",
          "pron": "",
          "morph": "",
          "root": "",
          "kor": ""
        },
        {
          "text": "כִּי־יְרֵא",
          "meaning": "",
          "pron": "",
          "morph": "",
          "root": "",
          "kor": ""
        },
        {
          "text": "אֱלֹהִים",
          "meaning": "",
          "pron": "",
          "morph": "",
          "root": "",
          "kor": ""
        },
        {
          "text": "אַתָּה",
          "meaning": "",
          "pron": "",
          "morph": "",
          "root": "",
          "kor": ""
        },
        {
          "text": "וְלֹא",
          "meaning": "",
          "pron": "",
          "morph": "",
          "root": "",
          "kor": ""
        },
        {
          "text": "חָשַׂכְתָּ",
          "meaning": "",
          "pron": "",
          "morph": "",
          "root": "",
          "kor": ""
        },
        {
          "text": "אֶת־בִּנְךָ",
          "meaning": "",
          "pron": "",
          "morph": "",
          "root": "",
          "kor": ""
        },
        {
          "text": "אֶת־יְחִידְךָ",
          "meaning": "",
          "pron": "",
          "morph": "",
          "root": "",
          "kor": ""
        },
        {
          "text": "מִמֶּנִּי׃",
          "meaning": "",
          "pron": "",
          "morph": "",
          "root": "",
          "kor": ""
        }
      ]
    },
    "13": {
      "reference": "창세기 22:13",
      "verseText": "וַיִּשָּׂא אַבְרָהָם אֶת־עֵינָיו וַיַּרְא וְהִנֵּה־אַיִל אַחַר נֶאֱחַז בַּסְּבַךְ בְּקַרְנָיו וַיֵּלֶךְ אַבְרָהָם וַיִּקַּח אֶת־הָאַיִל וַיַּעֲלֵהוּ לְעֹלָה תַּחַת בְּנוֹ׃",
      "kor2": "그리고-들었다 아브라함 את-눈-그의 그리고-보았다 그리고-보라 숫양 אחד 붙잡혔다 ב-수풀 ב-뿔-그의 그리고-갔다 아브라함 그리고-취하였다 את-그-숫양 그리고-올렸다 אותו 번제로 תחת 아들-그의",
      "words": [
        {
          "text": "וַיִּשָּׂא",
          "meaning": "",
          "pron": "",
          "morph": "",
          "root": "",
          "kor": ""
        },
        {
          "text": "אַבְרָהָם",
          "meaning": "",
          "pron": "",
          "morph": "",
          "root": "",
          "kor": ""
        },
        {
          "text": "אֶת־עֵינָיו",
          "meaning": "",
          "pron": "",
          "morph": "",
          "root": "",
          "kor": ""
        },
        {
          "text": "וַיַּרְא",
          "meaning": "",
          "pron": "",
          "morph": "",
          "root": "",
          "kor": ""
        },
        {
          "text": "וְהִנֵּה־אַיִל",
          "meaning": "",
          "pron": "",
          "morph": "",
          "root": "",
          "kor": ""
        },
        {
          "text": "אַחַר",
          "meaning": "",
          "pron": "",
          "morph": "",
          "root": "",
          "kor": ""
        },
        {
          "text": "נֶאֱחַז",
          "meaning": "",
          "pron": "",
          "morph": "",
          "root": "",
          "kor": ""
        },
        {
          "text": "בַּסְּבַךְ",
          "meaning": "",
          "pron": "",
          "morph": "",
          "root": "",
          "kor": ""
        },
        {
          "text": "בְּקַרְנָיו",
          "meaning": "",
          "pron": "",
          "morph": "",
          "root": "",
          "kor": ""
        },
        {
          "text": "וַיֵּלֶךְ",
          "meaning": "",
          "pron": "",
          "morph": "",
          "root": "",
          "kor": ""
        },
        {
          "text": "אַבְרָהָם",
          "meaning": "",
          "pron": "",
          "morph": "",
          "root": "",
          "kor": ""
        },
        {
          "text": "וַיִּקַּח",
          "meaning": "",
          "pron": "",
          "morph": "",
          "root": "",
          "kor": ""
        },
        {
          "text": "אֶת־הָאַיִל",
          "meaning": "",
          "pron": "",
          "morph": "",
          "root": "",
          "kor": ""
        },
        {
          "text": "וַיַּעֲלֵהוּ",
          "meaning": "",
          "pron": "",
          "morph": "",
          "root": "",
          "kor": ""
        },
        {
          "text": "לְעֹלָה",
          "meaning": "",
          "pron": "",
          "morph": "",
          "root": "",
          "kor": ""
        },
        {
          "text": "תַּחַת",
          "meaning": "",
          "pron": "",
          "morph": "",
          "root": "",
          "kor": ""
        },
        {
          "text": "בְּנוֹ׃",
          "meaning": "",
          "pron": "",
          "morph": "",
          "root": "",
          "kor": ""
        }
      ]
    },
    "14": {
      "reference": "창세기 22:14",
      "verseText": "וַיִּקְרָא אַבְרָהָם שֵׁם־הַמָּקוֹם הַהוּא יְהוָה יִרְאֶה אֲשֶׁר יֵאָמֵר הַיּוֹם בְּהַר יְהוָה יֵרָאֶה׃",
      "kor2": "그리고-불렀다 아브라함 이름-그-장소 그-그것 יהוה יראה אשר 말해질 것이다 그-오늘 ב-산 יהוה יראה",
      "words": [
        {
          "text": "וַיִּקְרָא",
          "meaning": "",
          "pron": "",
          "morph": "",
          "root": "",
          "kor": ""
        },
        {
          "text": "אַבְרָהָם",
          "meaning": "",
          "pron": "",
          "morph": "",
          "root": "",
          "kor": ""
        },
        {
          "text": "שֵׁם־הַמָּקוֹם",
          "meaning": "",
          "pron": "",
          "morph": "",
          "root": "",
          "kor": ""
        },
        {
          "text": "הַהוּא",
          "meaning": "",
          "pron": "",
          "morph": "",
          "root": "",
          "kor": ""
        },
        {
          "text": "יְהוָה",
          "meaning": "",
          "pron": "",
          "morph": "",
          "root": "",
          "kor": ""
        },
        {
          "text": "יִרְאֶה",
          "meaning": "",
          "pron": "",
          "morph": "",
          "root": "",
          "kor": ""
        },
        {
          "text": "אֲשֶׁר",
          "meaning": "",
          "pron": "",
          "morph": "",
          "root": "",
          "kor": ""
        },
        {
          "text": "יֵאָמֵר",
          "meaning": "",
          "pron": "",
          "morph": "",
          "root": "",
          "kor": ""
        },
        {
          "text": "הַיּוֹם",
          "meaning": "",
          "pron": "",
          "morph": "",
          "root": "",
          "kor": ""
        },
        {
          "text": "בְּהַר",
          "meaning": "",
          "pron": "",
          "morph": "",
          "root": "",
          "kor": ""
        },
        {
          "text": "יְהוָה",
          "meaning": "",
          "pron": "",
          "morph": "",
          "root": "",
          "kor": ""
        },
        {
          "text": "יֵרָאֶה׃",
          "meaning": "",
          "pron": "",
          "morph": "",
          "root": "",
          "kor": ""
        }
      ]
    },
    "15": {
      "reference": "창세기 22:15",
      "verseText": "וַיִּקְרָא מַלְאַךְ יְהוָה אֶל־אַבְרָהָם שֵׁנִית מִן־הַשָּׁמָיִם׃",
      "kor2": "그리고-불렀다 천사 יהוה אל-아브라함 두번째 מן-그-하늘들",
      "words": [
        {
          "text": "וַיִּקְרָא",
          "meaning": "",
          "pron": "",
          "morph": "",
          "root": "",
          "kor": ""
        },
        {
          "text": "מַלְאַךְ",
          "meaning": "",
          "pron": "",
          "morph": "",
          "root": "",
          "kor": ""
        },
        {
          "text": "יְהוָה",
          "meaning": "",
          "pron": "",
          "morph": "",
          "root": "",
          "kor": ""
        },
        {
          "text": "אֶל־אַבְרָהָם",
          "meaning": "",
          "pron": "",
          "morph": "",
          "root": "",
          "kor": ""
        },
        {
          "text": "שֵׁנִית",
          "meaning": "",
          "pron": "",
          "morph": "",
          "root": "",
          "kor": ""
        },
        {
          "text": "מִן־הַשָּׁמָיִם׃",
          "meaning": "",
          "pron": "",
          "morph": "",
          "root": "",
          "kor": ""
        }
      ]
    },
    "16": {
      "reference": "창세기 22:16",
      "verseText": "וַיֹּאמֶר בִּי נִשְׁבַּעְתִּי נְאֻם־יְהוָה כִּי יַעַן אֲשֶׁר עָשִׂיתָ אֶת־הַדָּבָר הַזֶּה וְלֹא חָשַׂכְתָּ אֶת־בִּנְךָ אֶת־יְחִידֶךָ׃",
      "kor2": "그리고-말하였다 나로 맹세하였다 말씀-יהוה כי 때문 אשר 행하였다 את-그-일 그-이것 그리고-아끼지-않았다 את-아들-네 את-유일한-네",
      "words": [
        {
          "text": "וַיֹּאמֶר",
          "meaning": "",
          "pron": "",
          "morph": "",
          "root": "",
          "kor": ""
        },
        {
          "text": "בִּי",
          "meaning": "",
          "pron": "",
          "morph": "",
          "root": "",
          "kor": ""
        },
        {
          "text": "נִשְׁבַּעְתִּי",
          "meaning": "",
          "pron": "",
          "morph": "",
          "root": "",
          "kor": ""
        },
        {
          "text": "נְאֻם־יְהוָה",
          "meaning": "",
          "pron": "",
          "morph": "",
          "root": "",
          "kor": ""
        },
        {
          "text": "כִּי",
          "meaning": "",
          "pron": "",
          "morph": "",
          "root": "",
          "kor": ""
        },
        {
          "text": "יַעַן",
          "meaning": "",
          "pron": "",
          "morph": "",
          "root": "",
          "kor": ""
        },
        {
          "text": "אֲשֶׁר",
          "meaning": "",
          "pron": "",
          "morph": "",
          "root": "",
          "kor": ""
        },
        {
          "text": "עָשִׂיתָ",
          "meaning": "",
          "pron": "",
          "morph": "",
          "root": "",
          "kor": ""
        },
        {
          "text": "אֶת־הַדָּבָר",
          "meaning": "",
          "pron": "",
          "morph": "",
          "root": "",
          "kor": ""
        },
        {
          "text": "הַזֶּה",
          "meaning": "",
          "pron": "",
          "morph": "",
          "root": "",
          "kor": ""
        },
        {
          "text": "וְלֹא",
          "meaning": "",
          "pron": "",
          "morph": "",
          "root": "",
          "kor": ""
        },
        {
          "text": "חָשַׂכְתָּ",
          "meaning": "",
          "pron": "",
          "morph": "",
          "root": "",
          "kor": ""
        },
        {
          "text": "אֶת־בִּנְךָ",
          "meaning": "",
          "pron": "",
          "morph": "",
          "root": "",
          "kor": ""
        },
        {
          "text": "אֶת־יְחִידֶךָ׃",
          "meaning": "",
          "pron": "",
          "morph": "",
          "root": "",
          "kor": ""
        }
      ]
    },
    "17": {
      "reference": "창세기 22:17",
      "verseText": "כִּי־בָרֵךְ אֲבָרֶכְךָ וְהַרְבָּה אַרְבֶּה אֶת־זַרְעֲךָ כְּכוֹכְבֵי הַשָּׁמַיִם וְכַחֹול אֲשֶׁר עַל־שְׂפַת הַיָּם וְיִרַשׁ זַרְעֲךָ אֵת שַׁעַר אֹיְבָיו׃",
      "kor2": "כי-복-주며 복-주겠다-너 그리고-많게 하며 많게-하겠다 את-씨-네 כ-별들 그-하늘들 그리고-כ-모래 אשר על-입술 그-바다 그리고-차지할 것이다 씨-네 את שער 적-그의",
      "words": [
        {
          "text": "כִּי־בָרֵךְ",
          "meaning": "",
          "pron": "",
          "morph": "",
          "root": "",
          "kor": ""
        },
        {
          "text": "אֲבָרֶכְךָ",
          "meaning": "",
          "pron": "",
          "morph": "",
          "root": "",
          "kor": ""
        },
        {
          "text": "וְהַרְבָּה",
          "meaning": "",
          "pron": "",
          "morph": "",
          "root": "",
          "kor": ""
        },
        {
          "text": "אַרְבֶּה",
          "meaning": "",
          "pron": "",
          "morph": "",
          "root": "",
          "kor": ""
        },
        {
          "text": "אֶת־זַרְעֲךָ",
          "meaning": "",
          "pron": "",
          "morph": "",
          "root": "",
          "kor": ""
        },
        {
          "text": "כְּכוֹכְבֵי",
          "meaning": "",
          "pron": "",
          "morph": "",
          "root": "",
          "kor": ""
        },
        {
          "text": "הַשָּׁמַיִם",
          "meaning": "",
          "pron": "",
          "morph": "",
          "root": "",
          "kor": ""
        },
        {
          "text": "וְכַחֹול",
          "meaning": "",
          "pron": "",
          "morph": "",
          "root": "",
          "kor": ""
        },
        {
          "text": "אֲשֶׁר",
          "meaning": "",
          "pron": "",
          "morph": "",
          "root": "",
          "kor": ""
        },
        {
          "text": "עַל־שְׂפַת",
          "meaning": "",
          "pron": "",
          "morph": "",
          "root": "",
          "kor": ""
        },
        {
          "text": "הַיָּם",
          "meaning": "",
          "pron": "",
          "morph": "",
          "root": "",
          "kor": ""
        },
        {
          "text": "וְיִרַשׁ",
          "meaning": "",
          "pron": "",
          "morph": "",
          "root": "",
          "kor": ""
        },
        {
          "text": "זַרְעֲךָ",
          "meaning": "",
          "pron": "",
          "morph": "",
          "root": "",
          "kor": ""
        },
        {
          "text": "אֵת",
          "meaning": "",
          "pron": "",
          "morph": "",
          "root": "",
          "kor": ""
        },
        {
          "text": "שַׁעַר",
          "meaning": "",
          "pron": "",
          "morph": "",
          "root": "",
          "kor": ""
        },
        {
          "text": "אֹיְבָיו׃",
          "meaning": "",
          "pron": "",
          "morph": "",
          "root": "",
          "kor": ""
        }
      ]
    },
    "18": {
      "reference": "창세기 22:18",
      "verseText": "וְהִתְבָּרֲכוּ בְּזַרְעֲךָ כֹּל גּוֹיֵי הָאָרֶץ עֵקֶב אֲשֶׁר שָׁמַעְתָּ בְּקֹלִי׃",
      "kor2": "그리고-복-얻을 것이다 ב-씨-네 모든 민족들 그-땅 עקב אשר 들었다 ב-음성-나의",
      "words": [
        {
          "text": "וְהִתְבָּרֲכוּ",
          "meaning": "",
          "pron": "",
          "morph": "",
          "root": "",
          "kor": ""
        },
        {
          "text": "בְּזַרְעֲךָ",
          "meaning": "",
          "pron": "",
          "morph": "",
          "root": "",
          "kor": ""
        },
        {
          "text": "כֹּל",
          "meaning": "",
          "pron": "",
          "morph": "",
          "root": "",
          "kor": ""
        },
        {
          "text": "גּוֹיֵי",
          "meaning": "",
          "pron": "",
          "morph": "",
          "root": "",
          "kor": ""
        },
        {
          "text": "הָאָרֶץ",
          "meaning": "",
          "pron": "",
          "morph": "",
          "root": "",
          "kor": ""
        },
        {
          "text": "עֵקֶב",
          "meaning": "",
          "pron": "",
          "morph": "",
          "root": "",
          "kor": ""
        },
        {
          "text": "אֲשֶׁר",
          "meaning": "",
          "pron": "",
          "morph": "",
          "root": "",
          "kor": ""
        },
        {
          "text": "שָׁמַעְתָּ",
          "meaning": "",
          "pron": "",
          "morph": "",
          "root": "",
          "kor": ""
        },
        {
          "text": "בְּקֹלִי׃",
          "meaning": "",
          "pron": "",
          "morph": "",
          "root": "",
          "kor": ""
        }
      ]
    },
    "19": {
      "reference": "창세기 22:19",
      "verseText": "וַיָּשָׁב אַבְרָהָם אֶל־נְעָרָיו וַיָּקֻמוּ וַיֵּלְכוּ יַחְדָּו אֶל־בְּאֵר שָׁבַע וַיֵּשֶׁב אַבְרָהָם בִּבְאֵר שָׁבַע׃",
      "kor2": "그리고-돌아왔다 아브라함 אל-소년들-그의 그리고-일어났다 그리고-갔다 함께 אל-브엘-세바 그리고-거하였다 아브라함 ב-브엘-세바",
      "words": [
        {
          "text": "וַיָּשָׁב",
          "meaning": "",
          "pron": "",
          "morph": "",
          "root": "",
          "kor": ""
        },
        {
          "text": "אַבְרָהָם",
          "meaning": "",
          "pron": "",
          "morph": "",
          "root": "",
          "kor": ""
        },
        {
          "text": "אֶל־נְעָרָיו",
          "meaning": "",
          "pron": "",
          "morph": "",
          "root": "",
          "kor": ""
        },
        {
          "text": "וַיָּקֻמוּ",
          "meaning": "",
          "pron": "",
          "morph": "",
          "root": "",
          "kor": ""
        },
        {
          "text": "וַיֵּלְכוּ",
          "meaning": "",
          "pron": "",
          "morph": "",
          "root": "",
          "kor": ""
        },
        {
          "text": "יַחְדָּו",
          "meaning": "",
          "pron": "",
          "morph": "",
          "root": "",
          "kor": ""
        },
        {
          "text": "אֶל־בְּאֵר",
          "meaning": "",
          "pron": "",
          "morph": "",
          "root": "",
          "kor": ""
        },
        {
          "text": "שָׁבַע",
          "meaning": "",
          "pron": "",
          "morph": "",
          "root": "",
          "kor": ""
        },
        {
          "text": "וַיֵּשֶׁב",
          "meaning": "",
          "pron": "",
          "morph": "",
          "root": "",
          "kor": ""
        },
        {
          "text": "אַבְרָהָם",
          "meaning": "",
          "pron": "",
          "morph": "",
          "root": "",
          "kor": ""
        },
        {
          "text": "בִּבְאֵר",
          "meaning": "",
          "pron": "",
          "morph": "",
          "root": "",
          "kor": ""
        },
        {
          "text": "שָׁבַע׃",
          "meaning": "",
          "pron": "",
          "morph": "",
          "root": "",
          "kor": ""
        }
      ]
    },
    "20": {
      "reference": "창세기 22:20",
      "verseText": "וַיְהִי אַחֲרֵי הַדְּבָרִים הָאֵלֶּה וַיֻּגַּד לְאַבְרָהָם לֵאמֹר הִנֵּה יָלְדָה מִלְכָּה גַּם־הִוא בָּנִים לְנָחוֹר אָחִיךָ׃",
      "kor2": "그리고-있었다 אחרי 그-일들 그-이것들 그리고-알려졌다 ל-아브라함 말하여 보라 낳았다 밀가 גם-היא 아들들 ל-나홀 형제-네",
      "words": [
        {
          "text": "וַיְהִי",
          "meaning": "",
          "pron": "",
          "morph": "",
          "root": "",
          "kor": ""
        },
        {
          "text": "אַחֲרֵי",
          "meaning": "",
          "pron": "",
          "morph": "",
          "root": "",
          "kor": ""
        },
        {
          "text": "הַדְּבָרִים",
          "meaning": "",
          "pron": "",
          "morph": "",
          "root": "",
          "kor": ""
        },
        {
          "text": "הָאֵלֶּה",
          "meaning": "",
          "pron": "",
          "morph": "",
          "root": "",
          "kor": ""
        },
        {
          "text": "וַיֻּגַּד",
          "meaning": "",
          "pron": "",
          "morph": "",
          "root": "",
          "kor": ""
        },
        {
          "text": "לְאַבְרָהָם",
          "meaning": "",
          "pron": "",
          "morph": "",
          "root": "",
          "kor": ""
        },
        {
          "text": "לֵאמֹר",
          "meaning": "",
          "pron": "",
          "morph": "",
          "root": "",
          "kor": ""
        },
        {
          "text": "הִנֵּה",
          "meaning": "",
          "pron": "",
          "morph": "",
          "root": "",
          "kor": ""
        },
        {
          "text": "יָלְדָה",
          "meaning": "",
          "pron": "",
          "morph": "",
          "root": "",
          "kor": ""
        },
        {
          "text": "מִלְכָּה",
          "meaning": "",
          "pron": "",
          "morph": "",
          "root": "",
          "kor": ""
        },
        {
          "text": "גַּם־הִוא",
          "meaning": "",
          "pron": "",
          "morph": "",
          "root": "",
          "kor": ""
        },
        {
          "text": "בָּנִים",
          "meaning": "",
          "pron": "",
          "morph": "",
          "root": "",
          "kor": ""
        },
        {
          "text": "לְנָחוֹר",
          "meaning": "",
          "pron": "",
          "morph": "",
          "root": "",
          "kor": ""
        },
        {
          "text": "אָחִיךָ׃",
          "meaning": "",
          "pron": "",
          "morph": "",
          "root": "",
          "kor": ""
        }
      ]
    },
    "21": {
      "reference": "창세기 22:21",
      "verseText": "אֶת־עוּץ בְּכֹרוֹ וְאֶת־בּוּז אָחִיו וְאֶת־קְמוּאֵל אֲבִי אֲרָם׃",
      "kor2": "את-우스 장자-그의 그리고-את 부스 형제-그의 그리고-את 그무엘 아버지 아람",
      "words": [
        {
          "text": "אֶת־עוּץ",
          "meaning": "",
          "pron": "",
          "morph": "",
          "root": "",
          "kor": ""
        },
        {
          "text": "בְּכֹרוֹ",
          "meaning": "",
          "pron": "",
          "morph": "",
          "root": "",
          "kor": ""
        },
        {
          "text": "וְאֶת־בּוּז",
          "meaning": "",
          "pron": "",
          "morph": "",
          "root": "",
          "kor": ""
        },
        {
          "text": "אָחִיו",
          "meaning": "",
          "pron": "",
          "morph": "",
          "root": "",
          "kor": ""
        },
        {
          "text": "וְאֶת־קְמוּאֵל",
          "meaning": "",
          "pron": "",
          "morph": "",
          "root": "",
          "kor": ""
        },
        {
          "text": "אֲבִי",
          "meaning": "",
          "pron": "",
          "morph": "",
          "root": "",
          "kor": ""
        },
        {
          "text": "אֲרָם׃",
          "meaning": "",
          "pron": "",
          "morph": "",
          "root": "",
          "kor": ""
        }
      ]
    },
    "22": {
      "reference": "창세기 22:22",
      "verseText": "וְאֶת־כֶּשֶׂד וְאֶת־חֲזוֹ וְאֶת־פִּלְדָּשׁ וְאֶת־יִדְלָף וְאֵת בְּתוּאֵל׃",
      "kor2": "그리고-את 게셋 그리고-את 하소 그리고-את 빌다스 그리고-את 이들랍 그리고-את 브두엘",
      "words": [
        {
          "text": "וְאֶת־כֶּשֶׂד",
          "meaning": "",
          "pron": "",
          "morph": "",
          "root": "",
          "kor": ""
        },
        {
          "text": "וְאֶת־חֲזוֹ",
          "meaning": "",
          "pron": "",
          "morph": "",
          "root": "",
          "kor": ""
        },
        {
          "text": "וְאֶת־פִּלְדָּשׁ",
          "meaning": "",
          "pron": "",
          "morph": "",
          "root": "",
          "kor": ""
        },
        {
          "text": "וְאֶת־יִדְלָף",
          "meaning": "",
          "pron": "",
          "morph": "",
          "root": "",
          "kor": ""
        },
        {
          "text": "וְאֵת",
          "meaning": "",
          "pron": "",
          "morph": "",
          "root": "",
          "kor": ""
        },
        {
          "text": "בְּתוּאֵל׃",
          "meaning": "",
          "pron": "",
          "morph": "",
          "root": "",
          "kor": ""
        }
      ]
    },
    "23": {
      "reference": "창세기 22:23",
      "verseText": "וּבְתוּאֵל יָלַד אֶת־רִבְקָה שְׁמֹנָה אֵלֶּה יָלְדָה מִלְכָּה לְנָחוֹר אֲחִי אַבְרָהָם׃",
      "kor2": "그리고-브두엘 낳았다 את-리브가 여덟 אלה 낳았다 밀가 ל-나홀 형제 아브라함",
      "words": [
        {
          "text": "וּבְתוּאֵל",
          "meaning": "",
          "pron": "",
          "morph": "",
          "root": "",
          "kor": ""
        },
        {
          "text": "יָלַד",
          "meaning": "",
          "pron": "",
          "morph": "",
          "root": "",
          "kor": ""
        },
        {
          "text": "אֶת־רִבְקָה",
          "meaning": "",
          "pron": "",
          "morph": "",
          "root": "",
          "kor": ""
        },
        {
          "text": "שְׁמֹנָה",
          "meaning": "",
          "pron": "",
          "morph": "",
          "root": "",
          "kor": ""
        },
        {
          "text": "אֵלֶּה",
          "meaning": "",
          "pron": "",
          "morph": "",
          "root": "",
          "kor": ""
        },
        {
          "text": "יָלְדָה",
          "meaning": "",
          "pron": "",
          "morph": "",
          "root": "",
          "kor": ""
        },
        {
          "text": "מִלְכָּה",
          "meaning": "",
          "pron": "",
          "morph": "",
          "root": "",
          "kor": ""
        },
        {
          "text": "לְנָחוֹר",
          "meaning": "",
          "pron": "",
          "morph": "",
          "root": "",
          "kor": ""
        },
        {
          "text": "אֲחִי",
          "meaning": "",
          "pron": "",
          "morph": "",
          "root": "",
          "kor": ""
        },
        {
          "text": "אַבְרָהָם׃",
          "meaning": "",
          "pron": "",
          "morph": "",
          "root": "",
          "kor": ""
        }
      ]
    },
    "24": {
      "reference": "창세기 22:24",
      "verseText": "וּפִילַגְשׁוֹ וּשְׁמָהּ רְאוּמָה וַתֵּלֶד גַּם־הִוא אֶת־טֶבַח וְאֶת־גַּחַם וְאֶת־תַּחַשׁ וְאֶת־מַעֲכָה׃",
      "kor2": "그리고-첩-그의 그리고-이름-그녀 르우마 그리고-낳았다 גם-היא את-데바 그리고-את 가함 그리고-את 다하스 그리고-את 마아가",
      "words": [
        {
          "text": "וּפִילַגְשׁוֹ",
          "meaning": "",
          "pron": "",
          "morph": "",
          "root": "",
          "kor": ""
        },
        {
          "text": "וּשְׁמָהּ",
          "meaning": "",
          "pron": "",
          "morph": "",
          "root": "",
          "kor": ""
        },
        {
          "text": "רְאוּמָה",
          "meaning": "",
          "pron": "",
          "morph": "",
          "root": "",
          "kor": ""
        },
        {
          "text": "וַתֵּלֶד",
          "meaning": "",
          "pron": "",
          "morph": "",
          "root": "",
          "kor": ""
        },
        {
          "text": "גַּם־הִוא",
          "meaning": "",
          "pron": "",
          "morph": "",
          "root": "",
          "kor": ""
        },
        {
          "text": "אֶת־טֶבַח",
          "meaning": "",
          "pron": "",
          "morph": "",
          "root": "",
          "kor": ""
        },
        {
          "text": "וְאֶת־גַּחַם",
          "meaning": "",
          "pron": "",
          "morph": "",
          "root": "",
          "kor": ""
        },
        {
          "text": "וְאֶת־תַּחַשׁ",
          "meaning": "",
          "pron": "",
          "morph": "",
          "root": "",
          "kor": ""
        },
        {
          "text": "וְאֶת־מַעֲכָה׃",
          "meaning": "",
          "pron": "",
          "morph": "",
          "root": "",
          "kor": ""
        }
      ]
    }
  }
}